[
    {
        "meta_datos":
        { 
        "sesion":1,
        "fecha":"15_08_2025",
        "participantes":
            { 
        "D":"Mujer",
        "DT":"Hombre",
        "AH":"Mujer",
        "AC":"Hombre"
            }
        }
    },
    {
        "entradas":{
"Habla espontánea
D: cuenteme que hizo ?
AH: yo  desayuné
D: qué más hizo? qué desayunó?
AH: sopa de verduras y atole
D: y pescado
D: que mas hizo en la semana?
AH: la tarea y  trapié
D: qué más?
AH: la tarea y duerme y duerme
D: qué otra cosa
AH: con mis nietos y con su esposa de Diego
D: diego quién es?
AH: mi nieto
D: la fueron a visitar?
AH: no,  aquí están en el departamento, a la mitad, como?
R: llegaron a rentar ahí
D: hizo alguna otra cosa, en las noches por ejemplo?
AH: café con leche y pan tostado 2
AH: el seguro también, me fui  al seguro 2
D: alguna otra cosa?
AH: el tianguis tambien , el miercoles
D: usted fue al tianguis?
AH: no porque ya no,  está muy feo, muy feo
D: porque es peligroso?
AH: sí
R: el llamado tianguis del salado

VERBOS Y SUSTANTIVOS CON APOYO VISUAL
Qué cosa es?
AH: estufa?
DT: muy bien, ahora por ejemplo este
AH: telefono
D: y a ver este
AH: cacerola
D. algo así
DT: un plato
DT: ahora este
AH: una taza, mhh cosa
DT: este de acá
AH: cuchillo
D: ¿Qué es?
AH: cuchillo
DT: parecido
D: atrás trae una pista
AH: tes?
AH: cuchillo?
DT: y a ver este
AH: una, que es, un
D: con qué sonido empieza?
AH: ta, ta ta
D: muy bien, empieza con ese sonido qué sigue
AH: una  corneta
D: no también es un instrumento pero no es una trompeta, dele la vuelta
AH: tambor (TAM)
DT: seguimos con cosa qué es?
AH: agua, el agua
DT:okay pero es un lugar y empieza con esta letra (M)
AH: mar
DT: a ver este
AH: que es? ay no, el metro
DT: este le va a gustar
AH: las galletas, las, el pan

DT: qué se hace?
AH: la taza estaba bien sabrosa
DT: la taza? se come?
AH: el café
DT: qué hace con el café?
AH: bien  sabroso, se hace con el café NP
D: se toma el café
DT: yo me tomé
D: yo tomé
DT: a ver esta
AH: el cuchillo
DT:que se hace
AH: el cuchillo está bien rasposo rasposoNP
DT:que hacemos con el cuchillo
AH: el cuchillo está bien filoso  NP
DT: y usted que hace con el cuchillo? para que lo usa
AH: aquí (señala su dedo) P
DT: que hizo usted
AH: esta bien ayyy bien filoso
DT: se cortó
AH: me corte*, el cuchillo
DT: vamos a intentar unos más y este?
DT: como se llama, vamos a usar la trampa (Cu)
AH: qué es?
DT: como lo usa, se come?
AH: nooo
DT: pero si se usa para …
AH: así (simula comer) 
DT: como se usa eso? comer
DT: no se acuerda como se llama?
DT: te..
AH: tendedor
DT: mas o menos
AH: ten…
DT: tene…
AH: tenedor
DT: para que se usa?
AH: el tenedor estaba haciendo-estaba haceERRFlexel tenedor  estaba haciendo-estabaPFIn sssssh (sorbe)*
DT: vamos a decir comió con el tenedor
AH: el tenedor, comi con el tenedor*

Qué se hace?
AH: leche con cafe
DT: este es un ejemplo, que se hace con el café pues me lo tomo
AH: si
DT: a ver esta qué me había dicho?
AH: la estufa
DT: y qué se hace con la estufa?
AH: se hace el café , en la estufa, con la estufa, la lumbre, en el café con leche 2
DT: y eso como se dice, cuando pone cosas aquí es cocinar, que se hace en la estufa?
AH: cocinar *
DT: o puede decir, yo cocino
AH: yo cocino, yo cociné*
DT: en la estufa
AH: yo cociné*
DT: ahora con este
AH: el telefono
DT: que hace
AH: rrrrrr
D: eso como se llama
AH: el telefono  estaba bien rue, rui  NP
D: tiene otra forma de decirlo, hace…
AH:  hace ruido
D: y usted que hace con el telefono
AH: hablo-con sus, con mis hijos mis-susPRSem  2
D: y usted que hace con sus hijos
AH:  estaba enel telefono, el telefono estar + L
D: en la estufa cocinamos y por el teléfono en el teléfono? hablamos o llamamos
AH: hablamos *
D: con esta que hacemos?
AH: la estufa
D: qué hacemos
AH:  cocinamos-estaba en la estufaFV x 
D: cocinamos
AH: cocinamos*
D: o yo cocino, y aquí?
AH: el telefono !!esta bien sordo  NP
DT: aquí
AH: las galletas
DT: que se hace con las galletas
AH: las galletas están bien sabrosas   P?
DT: qué hace usted con las galletas?
AH: las galletas estaban bien sabrosas [↑]
DT: aquí que dijimos que era?
DT: empieza con (M) esta letra
AH: mar
DT: aqui que hace ?
AH: el mar está bien feo   DS
DT: no le gusta? 
AH: no
DT: y que puede hacer en el mar?
AH: nadar-nadandoERRFlex nadando VGer P
DT: muy bien yo nado
AH: nadé nadé *
DT: esta qué es?
D: con que letra empieza? se acuerda?
DT: vamos a hacer trampa (ta)
A:la talla
AH: la cosa, que la.. ay mucha tristeza, mucha tristeza mi lengua

DT: a ver este que dijimos
AH: el metro
DT: y qué hace?
DT: eso como se llama
AH: el metro !!estaba acatitla NP
DT:: hace ruido?
AH: si mucho ruido*
DT: y va lento o rápido?
AH: pues lent, bien feo, bien
DT: se mueve?
AH: si hombre
DT: vamos a decir se mueve..usted diga, el metro… lo que usted quiera
AH: el metro estaba bien shh como? P
DT: lento?
AH: no, bien…
DT: rapido
AH: rapido bien rapido*
DT: se mueve
AH: el metro estaba bien
DT:rapido
AH: bien rapido
DT: a ver este a ver volteelo
AH: tambor
DT: que hace?
AH: tchtch (simula golpear un tambor con las manos)
DT: como se llama hacerle así?
AH: mucho ruido?
DT: okay..tocar el tambor
AH: tocar el ba, el tambor-tocadorPRSem, estaba el, qué es?
DT: el tambor, tocando el tambor o pegarle
AH: ah si
DT: el ultimo
AH: el plato
DT: que se puede hacer con el plato?
AH: servir-la sopaVInf
DT: se come? (el plato)
AH: no hombre
DT: se usa para la comida como?
AH: un plato con las cucharas y sopa
DT: entonces ..servimos la comida, a ver digalo
AH: servimos*
DT: o, yo sirvo
AH: yo sirvo sopa*

COSA O ACCIÓN
Confunde lapiz y escribir de categoría
DT:si le doy su tacita de cafe usted qué hace?
AH: bebí 
DT: tamal es cosa o es acción?
AH: cosa
DT: muy bien, que hace con el tamal
AH: no sé
DT: es comida
AH: si
DT: qué hace con la comida? (seña de comer)
AH: bebí
DT:nos lo co…
AH: comemos*
DT: este
AH: cuchillo
DT: es cosa o acción
AH: (clasifica en cosas)
DT: ¿Qué hace con el cuchillo?
DT: con el cuchillo qué se hizo
AH: cuchillo está bien filoso [↑]
DT: ¿Qué pasó, porque estaba filoso?
AH:  me machuque corté-machuquéPRSem
D: masomenos
DT: me cor…
AH: me corté*
DT: qué pasó con el cuchillo
AH: me corte*
DT: con
AH: con el cuchillo

Clasificación cosas acciones
DT: cepillar
AH: simula cepillar
A:cepillar*
DT:Donde va?
AH: aquí (acciones)
DT:muy bien y dientes?
AH: aquí (señala cosas)
DT: ahora digalo
AH: cepillar dientes*
DT: o como lo puede decir, yo…
AH: yo cepille los dientes*
DT: ahora con agua
AH: agua
DT: donde iría 
AH: (señala cosa pero al cuestionarla dice acción)
DT: y servir?
AH: aquí acción
DT: ver que es cosa o acción?
AH: (señala cosa) 
DT: segura
AH: acción 
DT: tele?
AH: coca, cosa
DT: muy bien

Sustantivo y verbo con dibujo
DT:con qué escribimos
AH: el lapiz
DT: que es esta parte
A:la goma
DT: y esta
AH: la goma
DT: se mueve solo el lapiz?
AH: no
DT: como se usa (toca su mano)
AH: con la mano"
    }}
]